docs/sphinx/source/conf.py
examples/forest_fires/python_walkthrough.py
examples/mass_shootings/python_walkthrough.py
examples/search_and_rescue/python_walkthrough.py
examples/ww2_bombings/python_walkthrough.py
geohexviz/__init__.py
geohexviz/builder.py
geohexviz/errors.py
geohexviz/simple.py
geohexviz/templates.py
geohexviz/utils/__init__.py
geohexviz/utils/colorscales.py
geohexviz/utils/file.py
geohexviz/utils/geoutils.py
geohexviz/utils/plot_util.py
geohexviz/utils/util.py
geohexviz-1.0.2.dist-info/LICENSE
geohexviz-1.0.2.dist-info/METADATA
geohexviz-1.0.2.dist-info/WHEEL
geohexviz-1.0.2.dist-info/entry_points.txt
geohexviz-1.0.2.dist-info/top_level.txt
geohexviz-1.0.2.dist-info/RECORD
