Metadata-Version: 2.1
Name: geohexviz
Version: 1.0.2
Summary: A library for the visualization of hexagonally binned data sets.
Home-page: 
Author: Tony Marco Abou Zeidan, Mark Rempel
Author-email: Tony Abou Zeidan <tony.azp25@gmail.com>, Mark Rempel <mark.rempel@forces.gc.ca>
License: MIT
Project-URL: Source, https://github.com/mrempel/geohexviz
Keywords: visualization,geospatial,hexagonal binning
Classifier: Programming Language :: Python :: 3
Classifier: Programming Language :: Python :: 3.7
Classifier: Programming Language :: Python :: 3.8
Classifier: Programming Language :: Python :: 3.9
Classifier: Programming Language :: Python :: 3.10
Classifier: Programming Language :: Python :: 3.11
Classifier: License :: OSI Approved :: MIT License
Classifier: Operating System :: OS Independent
Classifier: Topic :: Scientific/Engineering :: Information Analysis
Classifier: Topic :: Scientific/Engineering :: Visualization
Classifier: Topic :: Scientific/Engineering
Requires-Python: >=3.7
License-File: LICENSE
Requires-Dist: h3 (>=3.7.0)
Requires-Dist: shapely (>=1.8.5)
Requires-Dist: geojson (>=2.5.0)
Requires-Dist: plotly (>=4.14.3)
Requires-Dist: kaleido (>=0.2.1)
Requires-Dist: pyyaml (>=5.4.1)
Requires-Dist: rtree (>=0.9.7)
Requires-Dist: openpyxl (>=3.0.9)
Requires-Dist: pdfcropmargins
Provides-Extra: dev
Requires-Dist: pip ; extra == 'dev'
Requires-Dist: Sphinx ; extra == 'dev'
